pysdhstrip/__init__.py
pysdhstrip/cli.py
pysdhstrip/pysdhstrip.py
pysdhstrip-0.1.0.dist-info/entry_points.txt
pysdhstrip-0.1.0.dist-info/WHEEL
pysdhstrip-0.1.0.dist-info/METADATA
pysdhstrip-0.1.0.dist-info/RECORD
