Metadata-Version: 2.1
Name: pysdhstrip
Version: 0.1.0
Summary: Intelligent SDH stripper for SRT subtitles
License: MIT
Author-email: nyuszika7h <nyuszika7h@gmail.com>
Requires-Python: ~= 3.9
Requires-Dist: pysrt~=1.1
Requires-Dist: regex>=2022.7.25
Provides-Extra: cli
Requires-Dist: click~=8.1; extra == "cli"
Requires-Dist: cloup~=1.0; extra == "cli"
Requires-Dist: coloredlogs~=15.0; extra == "cli"
